ScientificMicroservices/__init__.py
ScientificMicroservices/functions.py
scientificmicroservices-1.0.4.dist-info/licenses/LICENSE
scientificmicroservices-1.0.4.dist-info/METADATA
scientificmicroservices-1.0.4.dist-info/WHEEL
scientificmicroservices-1.0.4.dist-info/top_level.txt
scientificmicroservices-1.0.4.dist-info/RECORD
